hdlg/__init__.py
hdlg/config.py
hdlg/hdd.py
hdlg/hdlg.py
hdlg/ui/__init__.py
hdlg/ui/app.qss
hdlg/ui/icons/hdd-white.svg
hdlg/ui/icons/hdd.svg
hdlg/ui/icons/info-circle.svg
hdlg/ui/icons/refresh.svg
hdlg/ui/main.py
hdlg/ui/main.ui
hdlg/ui/worker.py
hdlg/utils.py
hdlg-0.2.1.dist-info/entry_points.txt
hdlg-0.2.1.dist-info/LICENSE
hdlg-0.2.1.dist-info/WHEEL
hdlg-0.2.1.dist-info/METADATA
hdlg-0.2.1.dist-info/RECORD
