Metadata-Version: 2.1
Name: hdlg
Version: 0.2.1
Summary: Modern GUI for hdl-dump.
Home-page: https://github.com/rlaphoenix/hdlg
License: GPL-3.0-or-later
Keywords: ps2,hdl-dump,ps2-hdd,ps2-game-installer
Author: PHOENiX
Author-email: rlaphoenix@pm.me
Requires-Python: >=3.7,<3.11
Classifier: Development Status :: 3 - Alpha
Classifier: Intended Audience :: End Users/Desktop
Classifier: License :: OSI Approved :: GNU General Public License v3 or later (GPLv3+)
Classifier: Natural Language :: English
Classifier: Operating System :: Microsoft :: Windows
Classifier: Programming Language :: Python :: 3
Classifier: Programming Language :: Python :: 3.7
Classifier: Programming Language :: Python :: 3.8
Classifier: Programming Language :: Python :: 3.9
Classifier: Programming Language :: Python :: 3.10
Classifier: Topic :: Games/Entertainment
Requires-Dist: PySide2 (>=5.15.2.1,<6.0.0.0)
Requires-Dist: WMI (>=1.5.1,<2.0.0)
Requires-Dist: appdirs (>=1.4.4,<2.0.0)
Requires-Dist: pywin32 (==304)
Requires-Dist: toml (>=0.10.2,<0.11.0)
Project-URL: Bug Tracker, https://github.com/rlaphoenix/hdlg/issues
Project-URL: Changelog, https://github.com/rlaphoenix/hdlg/blob/master/CHANGELOG.md
Project-URL: Forums, https://github.com/rlaphoenix/hdlg/discussions
Project-URL: Repository, https://github.com/rlaphoenix/hdlg
